masterai_scrapy_extensions-2024.8.1.dist-info/METADATA
masterai_scrapy_extensions-2024.8.1.dist-info/WHEEL
masterai_scrapy_extensions/__init__.py
masterai_scrapy_extensions/logcolor.py
masterai_scrapy_extensions/logreport.py
masterai_scrapy_extensions-2024.8.1.dist-info/RECORD
