Metadata-Version: 2.1
Name: masterai-scrapy-extensions
Version: 2024.8.1
Summary: A Scrapy extension that report your log from your scraped data.
Keywords: scrapy,log,report,colorful
Author-Email: alexsuthree <alexsuthree@gmail.com>
License: MIT
Classifier: Programming Language :: Python :: 3
Classifier: License :: OSI Approved :: MIT License
Classifier: Operating System :: OS Independent
Requires-Python: ==3.11.*
Requires-Dist: scrapy>=2.11.2
Requires-Dist: build>=1.2.1
Requires-Dist: twine>=5.1.1
Requires-Dist: ipdb>=0.13.13
Requires-Dist: colorlog>=6.8.2
